bestLibraryEver/__init__.py
bestLibraryEver/bestLibraryEver.py
bestLibraryEver-0.0.8.dist-info/METADATA
bestLibraryEver-0.0.8.dist-info/WHEEL
bestLibraryEver-0.0.8.dist-info/top_level.txt
bestLibraryEver-0.0.8.dist-info/RECORD
