Metadata-Version: 2.1
Name: bestLibraryEver
Version: 0.0.8
Summary: A random base class package
Home-page: UNKNOWN
Author: Irakli Nozadze
License: UNKNOWN
Keywords: python
Platform: UNKNOWN
